{
  "$schema": "https://json-schema.org/draft/2020-12/schema",
  "$id": "https://redshield.dev/schemas/elements.schema.json",
  "title": "RedShield Model Elements",
  "type": "object",
  "additionalProperties": false,
  "required": ["schemaVersion", "elements"],
  "properties": {
    "schemaVersion": { "const": "0.1.0" },
    "elements": {
      "type": "array",
      "items": {
        "type": "object",
        "additionalProperties": false,
        "required": ["id", "kind", "name"],
        "properties": {
          "id": { "type": "string", "minLength": 1 },
          "kind": { "type": "string", "enum": ["actor", "use_case", "class", "component", "activity", "sequence_participant"] },
          "name": { "type": "string", "minLength": 1 },
          "aliases": { "type": "array", "items": { "type": "string", "minLength": 1 } },
          "description": { "type": "string" },
          "documentation": { "type": "string" },
          "status": { "type": "string", "enum": ["draft", "proposed", "accepted", "deprecated", "retired"] },
          "stereotypes": { "type": "array", "items": { "type": "string", "minLength": 1 } },
          "tags": { "type": "array", "items": { "type": "string", "minLength": 1 } },
          "provenance": { "$ref": "#/$defs/provenance" },
          "externalReferences": {
            "type": "array",
            "items": { "$ref": "#/$defs/externalReference" }
          },
          "classifier": { "$ref": "#/$defs/classifierDetails" }
        },
        "allOf": [
          {
            "if": { "required": ["classifier"] },
            "then": {
              "properties": {
                "kind": { "enum": ["class", "component"] }
              }
            }
          }
        ]
      }
    }
  },
  "$defs": {
    "provenance": {
      "type": "object",
      "additionalProperties": false,
      "properties": {
        "sourceRefs": {
          "type": "array",
          "items": { "type": "string", "minLength": 1 }
        },
        "createdBy": { "type": "string", "minLength": 1 },
        "createdAt": { "type": "string", "minLength": 1 },
        "notes": { "type": "string" }
      }
    },
    "externalReference": {
      "type": "object",
      "additionalProperties": false,
      "required": ["id", "label", "uri"],
      "properties": {
        "id": { "type": "string", "minLength": 1 },
        "label": { "type": "string", "minLength": 1 },
        "uri": { "type": "string", "minLength": 1 },
        "kind": { "type": "string", "minLength": 1 }
      }
    },
    "classifierDetails": {
      "type": "object",
      "additionalProperties": false,
      "properties": {
        "isAbstract": { "type": "boolean" },
        "isStatic": { "type": "boolean" },
        "attributes": {
          "type": "array",
          "items": { "$ref": "#/$defs/classifierAttribute" }
        },
        "operations": {
          "type": "array",
          "items": { "$ref": "#/$defs/classifierOperation" }
        }
      }
    },
    "classifierAttribute": {
      "type": "object",
      "additionalProperties": false,
      "required": ["name"],
      "properties": {
        "name": { "type": "string", "minLength": 1 },
        "visibility": { "$ref": "#/$defs/visibility" },
        "typeRef": { "type": "string", "minLength": 1 },
        "multiplicity": { "$ref": "#/$defs/multiplicity" },
        "defaultValue": { "type": "string" },
        "isStatic": { "type": "boolean" },
        "isReadOnly": { "type": "boolean" },
        "documentation": { "type": "string" }
      }
    },
    "classifierOperation": {
      "type": "object",
      "additionalProperties": false,
      "required": ["name"],
      "properties": {
        "name": { "type": "string", "minLength": 1 },
        "visibility": { "$ref": "#/$defs/visibility" },
        "returnTypeRef": { "type": "string", "minLength": 1 },
        "parameters": {
          "type": "array",
          "items": { "$ref": "#/$defs/operationParameter" }
        },
        "isAbstract": { "type": "boolean" },
        "isStatic": { "type": "boolean" },
        "documentation": { "type": "string" }
      }
    },
    "operationParameter": {
      "type": "object",
      "additionalProperties": false,
      "required": ["name"],
      "properties": {
        "name": { "type": "string", "minLength": 1 },
        "typeRef": { "type": "string", "minLength": 1 },
        "direction": { "type": "string", "enum": ["in", "out", "inout", "return"] },
        "multiplicity": { "$ref": "#/$defs/multiplicity" },
        "defaultValue": { "type": "string" }
      }
    },
    "multiplicity": {
      "type": "object",
      "additionalProperties": false,
      "properties": {
        "lower": { "type": "integer", "minimum": 0 },
        "upper": {
          "oneOf": [
            { "type": "integer", "minimum": 0 },
            { "const": "*" }
          ]
        },
        "isOrdered": { "type": "boolean" },
        "isUnique": { "type": "boolean" }
      }
    },
    "visibility": {
      "type": "string",
      "enum": ["public", "private", "protected", "package"]
    }
  }
}
